{
    "name": "OneTrust",
    "description": "OneTrust is a comprehensive privacy management and compliance platform used by organizations to navigate and adhere to various data privacy regulations.",
    "icon": "/icon/onetrust.png",
    "checks": {
        "tags": [
            {
                "tag": "script",
                "attribute": "src",
                "value": "geolocation.onetrust.com"
            },
            {
                "tag": "script",
                "attribute": "src",
                "value": "/otSDKStub.js"
            },
            {
                "tag": "script",
                "attribute": "src",
                "value": "/OtAutoBlock.js"
            }
        ],
        "headers": []
    }
}